encrypthis/__init__.py
encrypthis/cli.py
encrypthis/util.py
encrypthis/validators.py
encrypthis-0.1.0.dist-info/entry_points.txt
encrypthis-0.1.0.dist-info/WHEEL
encrypthis-0.1.0.dist-info/METADATA
encrypthis-0.1.0.dist-info/RECORD
