Metadata-Version: 2.1
Name: encrypthis
Version: 0.1.0
Summary: 
Author: 'Gilad Barnea'
Author-email: giladbrn@gmail.com
Requires-Python: >=3.8,<4.0
Classifier: Programming Language :: Python :: 3
Classifier: Programming Language :: Python :: 3.10
Classifier: Programming Language :: Python :: 3.8
Classifier: Programming Language :: Python :: 3.9
Requires-Dist: click (>=8.1.3,<9.0.0)
Requires-Dist: cryptography (>=37.0.4,<38.0.0)
